LockFileSemaphore/__init__.py
LockFileSemaphore/core.py
lockfilesemaphore-3.0.2.dist-info/licenses/LICENSE
lockfilesemaphore-3.0.2.dist-info/METADATA
lockfilesemaphore-3.0.2.dist-info/WHEEL
lockfilesemaphore-3.0.2.dist-info/top_level.txt
lockfilesemaphore-3.0.2.dist-info/RECORD
