Metadata-Version: 2.4
Name: LockFileSemaphore
Version: 3.0.2
Summary: Robust file-based semaphore with stale lock recovery and context manager support.
Author: Marcin Kowalczyk
Classifier: Programming Language :: Python :: 3
Classifier: Operating System :: OS Independent
Requires-Python: >=3.10
License-File: LICENSE
Dynamic: author
Dynamic: classifier
Dynamic: description
Dynamic: description-content-type
Dynamic: license-file
Dynamic: requires-python
Dynamic: summary
